todoforai_edge/__init__.py
todoforai_edge/app.py
todoforai_edge/arg_parser.py
todoforai_edge/colors.py
todoforai_edge/config.py
todoforai_edge/edge.py
todoforai_edge/edge_config.py
todoforai_edge/edge_functions.py
todoforai_edge/frontend_ws.py
todoforai_edge/mcp_collector.py
todoforai_edge/mcp_log_handler.py
todoforai_edge/observable.py
todoforai_edge/types.py
todoforai_edge/utils.py
todoforai_edge/constants/__init__.py
todoforai_edge/constants/constants.py
todoforai_edge/constants/messages.py
todoforai_edge/constants/workspace_handler.py
todoforai_edge/examples/todo_management_example.py
todoforai_edge/handlers/__init__.py
todoforai_edge/handlers/docx_handler.py
todoforai_edge/handlers/file_sync.py
todoforai_edge/handlers/handlers.py
todoforai_edge/handlers/path_utils.py
todoforai_edge/handlers/shell_handler.py
todoforai_edge_cli-0.12.2.dist-info/licenses/LICENSE
todoforai_edge_cli-0.12.2.dist-info/METADATA
todoforai_edge_cli-0.12.2.dist-info/WHEEL
todoforai_edge_cli-0.12.2.dist-info/entry_points.txt
todoforai_edge_cli-0.12.2.dist-info/top_level.txt
todoforai_edge_cli-0.12.2.dist-info/RECORD
