Metadata-Version: 2.4
Name: todoforai-edge-cli
Version: 0.12.2
Summary: TODO for AI service console client
Author: TODO for AI Team
License: MIT
Project-URL: Homepage, https://todofor.ai
Project-URL: Bug Tracker, https://github.com/todoforai/edge/issues
Classifier: Programming Language :: Python :: 3
Classifier: License :: OSI Approved :: MIT License
Classifier: Operating System :: OS Independent
Requires-Python: >=3.10
License-File: LICENSE
Requires-Dist: websockets>=15
Requires-Dist: requests>=2.25.0
Requires-Dist: python-dotenv>=0.19.0
Requires-Dist: watchdog>=4.0.0
Requires-Dist: fastmcp>=2.12.1
Requires-Dist: watchfiles
Requires-Dist: aiofiles
Requires-Dist: aiohttp>=3.8.0
Dynamic: license-file
